{"name":null,"assets":"aoy4:pathy48:assets%2FChallengeWeek%2Fimages%2Fbushvvhack.pngy4:sizei93008y4:typey5:IMAGEy2:idR1goR0y48:assets%2FChallengeWeek%2Fimages%2Fbushvvhack.xmlR2i1279R3y4:TEXTR5R6goR0y61:assets%2FChallengeWeek%2Fimages%2Ffive-minute-song%2FArm0.pngR2i83884R3R4R5R8goR0y61:assets%2FChallengeWeek%2Fimages%2Ffive-minute-song%2FArm1.pngR2i69410R3R4R5R9goR0y66:assets%2FChallengeWeek%2Fimages%2Ffive-minute-song%2FCablecrow.pngR2i3170701R3R4R5R10goR0y66:assets%2FChallengeWeek%2Fimages%2Ffive-minute-song%2FCablecrow.xmlR2i9351R3R7R5R11goR0y61:assets%2FChallengeWeek%2Fimages%2Ffive-minute-song%2FGrab.pngR2i341712R3R4R5R12goR0y60:assets%2FChallengeWeek%2Fimages%2Ffive-minute-song%2FMic.pngR2i162882R3R4R5R13goR0y65:assets%2FChallengeWeek%2Fimages%2Ffive-minute-song%2FZardy2BG.pngR2i24871702R3R4R5R14goR0y65:assets%2FChallengeWeek%2Fimages%2Ffive-minute-song%2FZardy2BG.xmlR2i1801R3R7R5R15goR0y66:assets%2FChallengeWeek%2Fimages%2Ffive-minute-song%2FZardyDark.pngR2i1165082R3R4R5R16goR0y66:assets%2FChallengeWeek%2Fimages%2Ffive-minute-song%2FZardyDark.xmlR2i12170R3R7R5R17goR0y77:assets%2FChallengeWeek%2Fimages%2Ffive-minute-song%2FZardyWeek2_BoyFriend.pngR2i6147463R3R4R5R18goR0y77:assets%2FChallengeWeek%2Fimages%2Ffive-minute-song%2FZardyWeek2_BoyFriend.xmlR2i82965R3R7R5R19goR0y73:assets%2FChallengeWeek%2Fimages%2Ffive-minute-song%2FZardyWeek2_Vines.pngR2i487530R3R4R5R20goR0y73:assets%2FChallengeWeek%2Fimages%2Ffive-minute-song%2FZardyWeek2_Vines.xmlR2i8843R3R7R5R21goR0y76:assets%2FChallengeWeek%2Fimages%2Ffive-minute-song%2FZardy_Dark_Portrait.pngR2i25848R3R4R5R22goR0y57:assets%2FChallengeWeek%2Fimages%2Ffoolhardy_menu_text.pngR2i85549R3R4R5R23goR0y57:assets%2FChallengeWeek%2Fimages%2Ffoolhardy_menu_text.xmlR2i1186R3R7R5R24goR0y42:assets%2FChallengeWeek%2Fimages%2FMaze.pngR2i15427814R3R4R5R25goR0y42:assets%2FChallengeWeek%2Fimages%2FMaze.xmlR2i2014R3R7R5R26goR0y54:assets%2FChallengeWeek%2Fimages%2Fplease_send_help.jpgR2i342991R3R4R5R27goR0y45:assets%2FChallengeWeek%2Fimages%2Fplishue.pngR2i60422R3R4R5R28goR0y45:assets%2FChallengeWeek%2Fimages%2Fplishue.xmlR2i1148R3R7R5R29goR0y59:assets%2FChallengeWeek%2Fimages%2Fspeech_bubble_talking.pngR2i56470R3R4R5R30goR0y59:assets%2FChallengeWeek%2Fimages%2Fspeech_bubble_talking.xmlR2i3858R3R7R5R31goR0y44:assets%2FChallengeWeek%2Fimages%2FSplash.pngR2i116068R3R4R5R32goR0y42:assets%2FChallengeWeek%2Fimages%2FZady.pngR2i47308R3R4R5R33goR0y43:assets%2FChallengeWeek%2Fimages%2FZardy.pngR2i1687795R3R4R5R34goR0y43:assets%2FChallengeWeek%2Fimages%2FZardy.xmlR2i12166R3R7R5R35goR0y47:assets%2FChallengeWeek%2Fimages%2FZardyPort.pngR2i32642R3R4R5R36goR0y49:assets%2FChallengeWeek%2Fimages%2FZardy_Plush.pngR2i87685R3R4R5R37goR0y49:assets%2FChallengeWeek%2Fsounds%2Fbf_axe_chop.oggR2i7181R3y5:SOUNDR5R38goR0y49:assets%2FChallengeWeek%2Fsounds%2Fbf_axe_chop.wavR2i78952R3R39R5R40goR0y56:assets%2FChallengeWeek%2Fsounds%2Fbf_grabbed_by_vine.oggR2i38912R3R39R5R41goR0y56:assets%2FChallengeWeek%2Fsounds%2Fbf_grabbed_by_vine.wavR2i137752R3R39R5R42goR0y48:assets%2FChallengeWeek%2Fsounds%2Fbf_mic_hit.oggR2i10225R3R39R5R43goR0y52:assets%2FChallengeWeek%2Fsounds%2Fbf_vine_defeat.oggR2i76817R3R39R5R44goR0y52:assets%2FChallengeWeek%2Fsounds%2Fbf_vine_defeat.wavR2i417104R3R39R5R45goR0y53:assets%2FChallengeWeek%2Fsounds%2Fcable_claw_fire.oggR2i13392R3R39R5R46goR0y53:assets%2FChallengeWeek%2Fsounds%2Fcable_claw_fire.wavR2i191878R3R39R5R47goR0y55:assets%2FChallengeWeek%2Fsounds%2Fcable_claw_impact.oggR2i49788R3R39R5R48goR0y55:assets%2FChallengeWeek%2Fsounds%2Fcable_claw_impact.wavR2i342226R3R39R5R49goR0y56:assets%2FChallengeWeek%2Fsounds%2Fcable_claw_retract.oggR2i114668R3R39R5R50goR0y56:assets%2FChallengeWeek%2Fsounds%2Fcable_claw_retract.wavR2i323040R3R39R5R51goR0y48:assets%2FChallengeWeek%2Fsounds%2Fgame_start.oggR2i109608R3R39R5R52goR0y48:assets%2FChallengeWeek%2Fsounds%2Fgame_start.wavR2i519290R3R39R5R53goR0y53:assets%2FChallengeWeek%2Fsounds%2Fjumpscare_sound.wavR2i595476R3R39R5R54goR0y50:assets%2FChallengeWeek%2Fsounds%2Fmicfuckinhit.oggR2i42438R3R39R5R55goR0y43:assets%2FChallengeWeek%2Fsounds%2Fzardy.oggR2i10101R3R39R5R56goR0y54:assets%2FChallengeWeek%2Fsounds%2Fzardy_mic_impact.oggR2i46267R3R39R5R57goR0y54:assets%2FChallengeWeek%2Fsounds%2Fzardy_mic_impact.wavR2i196104R3R39R5R58gh","rootPath":"../","version":2,"libraryArgs":[],"libraryType":null}